opensitua_database/__init__.py
opensitua_database/abstractdb.py
opensitua_database/http_utils.py
opensitua_database/jobsdb.py
opensitua_database/postgresdb.py
opensitua_database/settingsdb.py
opensitua_database/sqlite_utils.py
opensitua_database/sqlitedb.py
opensitua_database/usersdb.py
opensitua_database-0.0.120.dist-info/LICENSE
opensitua_database-0.0.120.dist-info/METADATA
opensitua_database-0.0.120.dist-info/WHEEL
opensitua_database-0.0.120.dist-info/top_level.txt
opensitua_database-0.0.120.dist-info/RECORD
