Metadata-Version: 2.1
Name: opensitua-database
Version: 0.0.120
Summary: A core database functions package
Home-page: https://github.com/valluzzi/opensitua_database.git
Author: Valerio Luzzi
Author-email: valluzzi@gmail.com
License: UNKNOWN
Platform: UNKNOWN
Classifier: Programming Language :: Python :: 3
Classifier: License :: OSI Approved :: MIT License
Classifier: Operating System :: OS Independent
Requires-Dist: opensitua-core
Requires-Dist: psycopg2
